{
  "_class": "text",
  "attributedString": {
    "_class": "attributedString",
    "attributes": [
      {
        "_class": "stringAttribute",
        "attributes": {
          "MSAttributedStringColorAttribute": {
            "_class": "color",
            "alpha": 1,
            "blue": 1,
            "green": 1,
            "red": 1
          },
          "MSAttributedStringFontAttribute": {
            "_class": "fontDescriptor",
            "attributes": {
              "name": "Futura-Medium",
              "size": 5.333333333333333
            }
          },
          "paragraphStyle": {
            "_class": "paragraphStyle",
            "alignment": 0
          },
          "textStyleVerticalAlignmentKey": 0
        },
        "length": 15,
        "location": 0
      }
    ],
    "string": "Events and News"
  },
  "automaticallyDrawOnUnderlyingPath": false,
  "do_objectID": "F5C28197-121D-4C2E-B9F7-B1C3E43BFC4F",
  "dontSynchroniseWithSymbol": false,
  "exportOptions": {
    "_class": "exportOptions",
    "do_objectID": "C0CB462B-6A7B-4E09-88E0-84048C672E7C",
    "exportFormats": [
    ],
    "includedLayerIds": [
    ],
    "layerOptions": 0,
    "shouldTrim": false
  },
  "frame": {
    "_class": "rect",
    "constrainProportions": false,
    "do_objectID": "4B880AE8-34F7-4617-9AA7-F91F29766CCE",
    "height": 7,
    "width": 42,
    "x": 13,
    "y": 559
  },
  "glyphBounds": "{{0, 1}, {42, 6}}",
  "isFlippedHorizontal": false,
  "isFlippedVertical": false,
  "isLocked": false,
  "isVisible": true,
  "layerListExpandedType": 0,
  "lineSpacingBehaviour": 2,
  "name": "Events and News Copy 3",
  "nameIsFixed": false,
  "resizingConstraint": 47,
  "resizingType": 0,
  "rotation": 0,
  "shouldBreakMaskChain": false,
  "style": {
    "_class": "style",
    "blur": {
      "_class": "blur",
      "center": "{0.5, 0.5}",
      "do_objectID": "0ED307FE-A903-4212-AC17-49E394A8B386",
      "isEnabled": false,
      "motionAngle": 0,
      "radius": 2.222222222222222,
      "type": 0
    },
    "do_objectID": "8F22EEFF-46A7-4AB9-8725-633D334D1192",
    "endDecorationType": 0,
    "miterLimit": 10,
    "startDecorationType": 0,
    "textStyle": {
      "_class": "textStyle",
      "do_objectID": "DB0D2D3B-E388-4759-B929-77E84622FFED",
      "encodedAttributes": {
        "MSAttributedStringColorAttribute": {
          "_class": "color",
          "alpha": 1,
          "blue": 1,
          "green": 1,
          "red": 1
        },
        "MSAttributedStringFontAttribute": {
          "_class": "fontDescriptor",
          "attributes": {
            "name": "Futura-Medium",
            "size": 5.333333333333333
          }
        },
        "paragraphStyle": {
          "_class": "paragraphStyle",
          "alignment": 0
        },
        "textStyleVerticalAlignmentKey": 0
      },
      "verticalAlignment": 0
    }
  },
  "textBehaviour": 0,
  "userInfo": {
    "com.invision.prototype": {
      "backgroundOpacity": 0,
      "closeOnClickOutside": 1,
      "componentType": "SRLink",
      "fixOverlayPosition": 1,
      "gesture": 0,
      "linkType": 0,
      "maintainScrollPositionAfterGesture": 0,
      "maintainScrollPositionAfterRedirect": 0,
      "openURLInNewWindow": 0,
      "overlayPosition": 0,
      "overlayTransition": 0,
      "redirectAfter": 0,
      "reverseTransitionOnClose": 1,
      "scrollToPosition": 0,
      "smoothScrolling": 0,
      "stayOnTargetScreen": 0,
      "targetArtboardID": "9EF3BBC0-101D-43AB-99FD-03623079F1F7",
      "transition": 0
    }
  }
}